numbat/__init__.py
numbat/api.py
numbat/db.py
numbat/exceptions.py
numbat/py.typed
numbat/types.py
numbat-0.2.6.dist-info/licenses/LICENSE
numbat-0.2.6.dist-info/METADATA
numbat-0.2.6.dist-info/WHEEL
numbat-0.2.6.dist-info/top_level.txt
numbat-0.2.6.dist-info/RECORD
