Metadata-Version: 2.4
Name: numbat
Version: 0.2.6
Summary: Library to manipulate and create Sourcetrail databases
Author-email: Eloïse Brocas <ebrocas@quarkslab.com>, Sami Babigeon <sbabigeon@quarkslab.com>
License: Apache License 2.0
Project-URL: Homepage, https://github.com/quarkslab/numbat
Project-URL: Source, https://github.com/quarkslab/numbat
Project-URL: Tracker, https://github.com/quarkslab/numbat/issues
Classifier: Development Status :: 4 - Beta
Classifier: Programming Language :: Python :: 3
Classifier: Operating System :: POSIX :: Linux
Classifier: Operating System :: Microsoft :: Windows
Classifier: Topic :: Software Development :: Libraries
Requires-Python: >=3.10
License-File: LICENSE
Provides-Extra: doc
Requires-Dist: black; extra == "doc"
Requires-Dist: mkdocs; extra == "doc"
Requires-Dist: mkdocs-autorefs; extra == "doc"
Requires-Dist: mkdocs-gen-files; extra == "doc"
Requires-Dist: mkdocs-glightbox; extra == "doc"
Requires-Dist: mkdocs-literate-nav; extra == "doc"
Requires-Dist: mkdocs-material; extra == "doc"
Requires-Dist: mkdocstrings-python; extra == "doc"
Requires-Dist: mkdocs-section-index; extra == "doc"
Provides-Extra: linting
Requires-Dist: ruff; extra == "linting"
Provides-Extra: test
Requires-Dist: pytest; extra == "test"
Provides-Extra: typechecking
Requires-Dist: mypy; extra == "typechecking"
Dynamic: license-file
